fmp_py_client/__init__.py
fmp_py_client/_base.py
fmp_py_client/_client.py
fmp_py_client/_exceptions.py
fmp_py_client/_types.py
fmp_py_client/api/__init__.py
fmp_py_client/api/_bulk.py
fmp_py_client/api/_calendar.py
fmp_py_client/api/_company.py
fmp_py_client/api/_crowdfunding.py
fmp_py_client/api/_economics.py
fmp_py_client/api/_esg.py
fmp_py_client/api/_etf.py
fmp_py_client/api/_financials.py
fmp_py_client/api/_government.py
fmp_py_client/api/_historical.py
fmp_py_client/api/_insider.py
fmp_py_client/api/_market.py
fmp_py_client/api/_mergers.py
fmp_py_client/api/_metrics.py
fmp_py_client/api/_movers.py
fmp_py_client/api/_news.py
fmp_py_client/api/_quotes.py
fmp_py_client/api/_search.py
fmp_py_client/api/_sec.py
fmp_py_client/api/_sector.py
fmp_py_client/api/_technical.py
fmp_py_client/api/_valuation.py
fmp_py_client/py.typed
fmp_py_client-0.1.0.dist-info/WHEEL
fmp_py_client-0.1.0.dist-info/METADATA
fmp_py_client-0.1.0.dist-info/RECORD
