Metadata-Version: 2.3
Name: fmp-py-client
Version: 0.1.0
Summary: Async Python client for Financial Modeling Prep API
Keywords: finance,api,stocks,financial-data,async,httpx
Author: Chengxu Bian
Author-email: Chengxu Bian <cbian564@gmail.com>
License: MIT
Classifier: Development Status :: 4 - Beta
Classifier: Intended Audience :: Developers
Classifier: Intended Audience :: Financial and Insurance Industry
Classifier: License :: OSI Approved :: MIT License
Classifier: Operating System :: OS Independent
Classifier: Programming Language :: Python :: 3
Classifier: Programming Language :: Python :: 3.12
Classifier: Programming Language :: Python :: 3.13
Classifier: Topic :: Office/Business :: Financial :: Investment
Classifier: Typing :: Typed
Classifier: Framework :: AsyncIO
Requires-Dist: httpx>=0.27
Requires-Python: >=3.12
Project-URL: Homepage, https://github.com/cbian/fmp-py-client
Project-URL: Documentation, https://cbian.github.io/fmp-py-client/
Project-URL: Repository, https://github.com/cbian/fmp-py-client
Project-URL: Issues, https://github.com/cbian/fmp-py-client/issues
